quantik_core/__init__.py
quantik_core/core.py
quantik_core/py.typed
quantik_core-0.1.1.dist-info/licenses/LICENSE
quantik_core-0.1.1.dist-info/METADATA
quantik_core-0.1.1.dist-info/WHEEL
quantik_core-0.1.1.dist-info/top_level.txt
quantik_core-0.1.1.dist-info/RECORD
