Metadata-Version: 2.4
Name: quantik-core
Version: 0.1.1
Summary: High-performance core utilities for Quantik game state manipulation
Author-email: Mauro Berlanda <mauro.berlanda@gmail.com>
License-Expression: MIT
Project-URL: Homepage, https://github.com/mauroberlanda/quantik-core-py
Project-URL: Repository, https://github.com/mauroberlanda/quantik-core-py
Project-URL: Documentation, https://quantik-core-py.readthedocs.io
Project-URL: Bug Tracker, https://github.com/mauroberlanda/quantik-core-py/issues
Keywords: quantik,board-games,game-ai,monte-carlo,bitboards,game-engine,mcts,game-theory,combinatorial-games
Classifier: Development Status :: 3 - Alpha
Classifier: Intended Audience :: Developers
Classifier: Intended Audience :: Science/Research
Classifier: Programming Language :: Python :: 3
Classifier: Programming Language :: Python :: 3.9
Classifier: Programming Language :: Python :: 3.10
Classifier: Programming Language :: Python :: 3.11
Classifier: Programming Language :: Python :: 3.12
Classifier: Programming Language :: Python :: 3.13
Classifier: Topic :: Games/Entertainment :: Board Games
Classifier: Topic :: Scientific/Engineering :: Artificial Intelligence
Classifier: Topic :: Software Development :: Libraries :: Python Modules
Requires-Python: >=3.9
License-File: LICENSE
Provides-Extra: dev
Requires-Dist: pytest>=7.0; extra == "dev"
Requires-Dist: pytest-cov>=4.0; extra == "dev"
Requires-Dist: hypothesis>=6.0; extra == "dev"
Requires-Dist: black>=23.0; extra == "dev"
Requires-Dist: flake8>=6.0; extra == "dev"
Requires-Dist: mypy>=1.0; extra == "dev"
Requires-Dist: pre-commit>=3.0; extra == "dev"
Provides-Extra: cbor
Requires-Dist: cbor2>=5.4.0; extra == "cbor"
Provides-Extra: docs
Requires-Dist: sphinx>=5.0; extra == "docs"
Requires-Dist: sphinx-rtd-theme>=1.0; extra == "docs"
Provides-Extra: benchmark
Requires-Dist: pytest-benchmark>=4.0; extra == "benchmark"
Provides-Extra: all
Requires-Dist: quantik-core[benchmark,cbor,dev,docs]; extra == "all"
Dynamic: license-file
